[
  {
    "summary_date": "2022-05-23",
    "period_id": 0,
    "is_longest": 1,
    "timezone": -240,
    "bedtime_end": "2022-05-24T09:15:40-04:00",
    "bedtime_start": "2022-05-24T00:43:40-04:00",
    "breath_average": 12,
    "duration": 30720,
    "total": 24630,
    "awake": 6090,
    "rem": 5880,
    "deep": 10680,
    "light": 8070,
    "midpoint_time": 14940,
    "efficiency": 80,
    "restless": 34,
    "onset_latency": 210,
    "hr_5min": [
      72,
      71,
      73,
      71,
      71,
      71,
      71,
      70,
      70,
      70,
      74,
      74,
      0,
      77,
      77,
      79,
      83,
      77,
      79,
      77,
      74,
      77,
      74,
      71,
      69,
      70,
      69,
      68,
      69,
      69,
      69,
      71,
      76,
      75,
      77,
      75,
      74,
      73,
      72,
      71,
      71,
      70,
      71,
      70,
      71,
      71,
      71,
      70,
      72,
      70,
      70,
      73,
      75,
      76,
      77,
      74,
      73,
      75,
      72,
      74,
      76,
      71,
      70,
      69,
      69,
      68,
      69,
      69,
      68,
      68,
      68,
      69,
      68,
      72,
      72,
      66,
      65,
      65,
      65,
      66,
      65,
      63,
      68,
      67,
      74,
      69,
      67,
      67,
      69,
      72,
      72,
      70,
      71,
      72,
      71,
      72,
      66,
      67,
      69,
      72,
      74,
      0,
      0
    ],
    "hr_average": 71.26,
    "hr_lowest": 63,
    "hypnogram_5min": "4211111111114444233334422111111113322211111111112322443444422221111222111133222122243332443333332334444",
    "rmssd": 40,
    "rmssd_5min": [
      18,
      34,
      46,
      36,
      26,
      20,
      35,
      36,
      39,
      44,
      43,
      32,
      0,
      19,
      26,
      18,
      14,
      18,
      17,
      31,
      32,
      32,
      32,
      50,
      56,
      57,
      62,
      58,
      55,
      55,
      44,
      41,
      17,
      23,
      20,
      20,
      26,
      29,
      36,
      39,
      40,
      42,
      32,
      35,
      37,
      39,
      38,
      42,
      57,
      47,
      42,
      29,
      26,
      21,
      28,
      28,
      26,
      33,
      37,
      33,
      36,
      43,
      46,
      50,
      56,
      53,
      52,
      57,
      51,
      55,
      52,
      54,
      53,
      38,
      33,
      46,
      45,
      47,
      48,
      50,
      51,
      41,
      43,
      38,
      17,
      50,
      42,
      58,
      43,
      31,
      43,
      37,
      36,
      31,
      36,
      38,
      32,
      39,
      37,
      49,
      37,
      0,
      0
    ],
    "score": 71,
    "score_alignment": 43,
    "score_deep": 100,
    "score_disturbances": 66,
    "score_efficiency": 72,
    "score_latency": 70,
    "score_rem": 80,
    "score_total": 70,
    "temperature_deviation": 0.17,
    "temperature_trend_deviation": 0.23,
    "bedtime_start_delta": 2620,
    "bedtime_end_delta": 33340,
    "midpoint_at_delta": 17560,
    "temperature_delta": 0.17
  }
]