[
  {
    "Rank": 1,
    "Time Spent (seconds)": 975,
    "Number of People": 1,
    "Category": "Utilities"
  },
  {
    "Rank": 2,
    "Time Spent (seconds)": 963,
    "Number of People": 1,
    "Category": "Social Networking"
  },
  {
    "Rank": 3,
    "Time Spent (seconds)": 662,
    "Number of People": 1,
    "Category": "Reference & Learning"
  },
  {
    "Rank": 4,
    "Time Spent (seconds)": 450,
    "Number of People": 1,
    "Category": "Uncategorized"
  },
  {
    "Rank": 5,
    "Time Spent (seconds)": 368,
    "Number of People": 1,
    "Category": "Communication & Scheduling"
  },
  {
    "Rank": 6,
    "Time Spent (seconds)": 33,
    "Number of People": 1,
    "Category": "Business"
  },
  {
    "Rank": 7,
    "Time Spent (seconds)": 2,
    "Number of People": 1,
    "Category": "Shopping"
  }
]