{
  "1": {},
  "2": {},
  "3": {},
  "4": {
    "Email": 10329,
    "Browsers": 44558,
    "General Social Networking": 35793,
    "Professional Networking": 10577,
    "Maps & Regional": 1010,
    "Video": 17034,
    "Uncategorized": 11596,
    "Instant Message": 27424,
    "General Utilities": 8414,
    "Search": 2918,
    "Health & Medicine": 1895,
    "Music": 4412,
    "General Shopping": 1548,
    "Clothes & Personal": 1498,
    "Voice Chat": 1236,
    "Calendars": 363,
    "General Reference & Learning": 200,
    "General Business": 1994,
    "Photos": 774,
    "Engineering & Technology": 176,
    "Science & Technology": 1600,
    "Project Management": 77,
    "General Entertainment": 666,
    "General Communication & Scheduling": 1199,
    "Business": 237,
    "General Software Development": 334,
    "Internet Utilities": 2,
    "Writing": 62,
    "Intelligence": 30,
    "General News & Opinion": 442
  },
  "5": {},
  "6": {},
  "7": {},
  "8": {},
  "9": {},
  "10": {},
  "11": {},
  "12": {}
}