{
  "1": {
    "Communication & Scheduling": 6688,
    "Utilities": 2882,
    "Social Networking": 1630,
    "Entertainment": 982,
    "Uncategorized": 435,
    "Reference & Learning": 150,
    "Business": 29,
    "News & Opinion": 21,
    "Shopping": 9
  },
  "2": {
    "Social Networking": 1822,
    "Communication & Scheduling": 1264,
    "Utilities": 1047,
    "Entertainment": 609,
    "Uncategorized": 242,
    "Reference & Learning": 230,
    "Business": 12
  },
  "3": {},
  "4": {},
  "5": {},
  "6": {},
  "7": {},
  "8": {},
  "9": {},
  "10": {},
  "11": {},
  "12": {},
  "13": {},
  "14": {},
  "15": {},
  "16": {},
  "17": {},
  "18": {},
  "19": {},
  "20": {},
  "21": {},
  "22": {},
  "23": {},
  "24": {},
  "25": {},
  "26": {},
  "27": {},
  "28": {},
  "29": {},
  "30": {}
}