[
  {
    "categories": [
      {
        "decimal": "1.35",
        "digital": "1:21:39",
        "hours": 1,
        "minutes": 21,
        "name": "Coding",
        "percent": 100,
        "seconds": 39,
        "text": "1 hr 21 mins",
        "total_seconds": 4899.098756
      }
    ],
    "dependencies": [
      {
        "decimal": "0.57",
        "digital": "0:34:39",
        "hours": 0,
        "minutes": 34,
        "name": "lodash",
        "percent": 5.07,
        "seconds": 39,
        "text": "34 mins",
        "total_seconds": 2079.690771
      },
      {
        "decimal": "0.55",
        "digital": "0:33:22",
        "hours": 0,
        "minutes": 33,
        "name": "media",
        "percent": 4.88,
        "seconds": 22,
        "text": "33 mins",
        "total_seconds": 2002.492155
      },
      {
        "decimal": "0.55",
        "digital": "0:33:06",
        "hours": 0,
        "minutes": 33,
        "name": "utils",
        "percent": 4.84,
        "seconds": 6,
        "text": "33 mins",
        "total_seconds": 1986.608314
      },
      {
        "decimal": "0.53",
        "digital": "0:32:23",
        "hours": 0,
        "minutes": 32,
        "name": "core",
        "percent": 4.74,
        "seconds": 23,
        "text": "32 mins",
        "total_seconds": 1943.511525
      },
      {
        "decimal": "0.50",
        "digital": "0:30:15",
        "hours": 0,
        "minutes": 30,
        "name": "services",
        "percent": 4.43,
        "seconds": 15,
        "text": "30 mins",
        "total_seconds": 1815.821472
      },
      {
        "decimal": "0.50",
        "digital": "0:30:08",
        "hours": 0,
        "minutes": 30,
        "name": "logger",
        "percent": 4.41,
        "seconds": 8,
        "text": "30 mins",
        "total_seconds": 1808.292096
      },
      {
        "decimal": "0.48",
        "digital": "0:29:57",
        "hours": 0,
        "minutes": 29,
        "name": "interfaces",
        "percent": 4.38,
        "seconds": 57,
        "text": "29 mins",
        "total_seconds": 1797.6277
      },
      {
        "decimal": "0.48",
        "digital": "0:29:50",
        "hours": 0,
        "minutes": 29,
        "name": "enum",
        "percent": 4.36,
        "seconds": 50,
        "text": "29 mins",
        "total_seconds": 1790.459811
      },
      {
        "decimal": "0.45",
        "digital": "0:27:38",
        "hours": 0,
        "minutes": 27,
        "name": "environment",
        "percent": 4.04,
        "seconds": 38,
        "text": "27 mins",
        "total_seconds": 1658.159501
      },
      {
        "decimal": "0.43",
        "digital": "0:26:19",
        "hours": 0,
        "minutes": 26,
        "name": "rxjs",
        "percent": 3.85,
        "seconds": 19,
        "text": "26 mins",
        "total_seconds": 1579.628733
      },
      {
        "decimal": "0.37",
        "digital": "0:22:45",
        "hours": 0,
        "minutes": 22,
        "name": "moment",
        "percent": 3.33,
        "seconds": 45,
        "text": "22 mins",
        "total_seconds": 1365.233594
      },
      {
        "decimal": "0.32",
        "digital": "0:19:15",
        "hours": 0,
        "minutes": 19,
        "name": "types",
        "percent": 2.82,
        "seconds": 15,
        "text": "19 mins",
        "total_seconds": 1155.154691
      },
      {
        "decimal": "0.32",
        "digital": "0:19:03",
        "hours": 0,
        "minutes": 19,
        "name": "filter.service",
        "percent": 2.79,
        "seconds": 3,
        "text": "19 mins",
        "total_seconds": 1143.149786
      },
      {
        "decimal": "0.23",
        "digital": "0:14:29",
        "hours": 0,
        "minutes": 14,
        "name": "paginator",
        "percent": 2.12,
        "seconds": 29,
        "text": "14 mins",
        "total_seconds": 869.802667
      },
      {
        "decimal": "0.23",
        "digital": "0:14:29",
        "hours": 0,
        "minutes": 14,
        "name": "table",
        "percent": 2.12,
        "seconds": 29,
        "text": "14 mins",
        "total_seconds": 869.802667
      },
      {
        "decimal": "0.23",
        "digital": "0:14:29",
        "hours": 0,
        "minutes": 14,
        "name": "sort",
        "percent": 2.12,
        "seconds": 29,
        "text": "14 mins",
        "total_seconds": 869.802667
      },
      {
        "decimal": "0.22",
        "digital": "0:13:08",
        "hours": 0,
        "minutes": 13,
        "name": "logrocket",
        "percent": 1.92,
        "seconds": 8,
        "text": "13 mins",
        "total_seconds": 788.356834
      },
      {
        "decimal": "0.22",
        "digital": "0:13:08",
        "hours": 0,
        "minutes": 13,
        "name": "amplitude-js",
        "percent": 1.92,
        "seconds": 8,
        "text": "13 mins",
        "total_seconds": 788.356834
      },
      {
        "decimal": "0.20",
        "digital": "0:12:16",
        "hours": 0,
        "minutes": 12,
        "name": "model",
        "percent": 1.79,
        "seconds": 16,
        "text": "12 mins",
        "total_seconds": 736.18635
      },
      {
        "decimal": "0.20",
        "digital": "0:12:01",
        "hours": 0,
        "minutes": 12,
        "name": "router",
        "percent": 1.76,
        "seconds": 1,
        "text": "12 mins",
        "total_seconds": 721.830971
      },
      {
        "decimal": "0.18",
        "digital": "0:11:54",
        "hours": 0,
        "minutes": 11,
        "name": "responses",
        "percent": 1.74,
        "seconds": 54,
        "text": "11 mins",
        "total_seconds": 714.348851
      },
      {
        "decimal": "0.18",
        "digital": "0:11:54",
        "hours": 0,
        "minutes": 11,
        "name": "express",
        "percent": 1.74,
        "seconds": 54,
        "text": "11 mins",
        "total_seconds": 714.348851
      },
      {
        "decimal": "0.18",
        "digital": "0:11:49",
        "hours": 0,
        "minutes": 11,
        "name": "en",
        "percent": 1.73,
        "seconds": 49,
        "text": "11 mins",
        "total_seconds": 709.826066
      },
      {
        "decimal": "0.18",
        "digital": "0:11:43",
        "hours": 0,
        "minutes": 11,
        "name": "notification",
        "percent": 1.72,
        "seconds": 43,
        "text": "11 mins",
        "total_seconds": 703.684455
      },
      {
        "decimal": "0.18",
        "digital": "0:11:43",
        "hours": 0,
        "minutes": 11,
        "name": "geolocation",
        "percent": 1.72,
        "seconds": 43,
        "text": "11 mins",
        "total_seconds": 703.684455
      },
      {
        "decimal": "0.18",
        "digital": "0:11:41",
        "hours": 0,
        "minutes": 11,
        "name": "webhook",
        "percent": 1.71,
        "seconds": 41,
        "text": "11 mins",
        "total_seconds": 701.736011
      },
      {
        "decimal": "0.18",
        "digital": "0:11:41",
        "hours": 0,
        "minutes": 11,
        "name": "templates",
        "percent": 1.71,
        "seconds": 41,
        "text": "11 mins",
        "total_seconds": 701.736011
      },
      {
        "decimal": "0.18",
        "digital": "0:11:41",
        "hours": 0,
        "minutes": 11,
        "name": "webhookController",
        "percent": 1.71,
        "seconds": 41,
        "text": "11 mins",
        "total_seconds": 701.736011
      },
      {
        "decimal": "0.18",
        "digital": "0:11:41",
        "hours": 0,
        "minutes": 11,
        "name": "payment",
        "percent": 1.71,
        "seconds": 41,
        "text": "11 mins",
        "total_seconds": 701.736011
      },
      {
        "decimal": "0.18",
        "digital": "0:11:37",
        "hours": 0,
        "minutes": 11,
        "name": "fs-extra",
        "percent": 1.7,
        "seconds": 37,
        "text": "11 mins",
        "total_seconds": 697.640969
      },
      {
        "decimal": "0.18",
        "digital": "0:11:37",
        "hours": 0,
        "minutes": 11,
        "name": "export",
        "percent": 1.7,
        "seconds": 37,
        "text": "11 mins",
        "total_seconds": 697.640969
      },
      {
        "decimal": "0.18",
        "digital": "0:11:37",
        "hours": 0,
        "minutes": 11,
        "name": "path",
        "percent": 1.7,
        "seconds": 37,
        "text": "11 mins",
        "total_seconds": 697.640969
      },
      {
        "decimal": "0.18",
        "digital": "0:11:37",
        "hours": 0,
        "minutes": 11,
        "name": "archiver",
        "percent": 1.7,
        "seconds": 37,
        "text": "11 mins",
        "total_seconds": 697.640969
      },
      {
        "decimal": "0.18",
        "digital": "0:11:37",
        "hours": 0,
        "minutes": 11,
        "name": "exportMedia",
        "percent": 1.7,
        "seconds": 37,
        "text": "11 mins",
        "total_seconds": 697.640969
      },
      {
        "decimal": "0.18",
        "digital": "0:11:37",
        "hours": 0,
        "minutes": 11,
        "name": "insightCategories",
        "percent": 1.7,
        "seconds": 37,
        "text": "11 mins",
        "total_seconds": 697.640969
      },
      {
        "decimal": "0.18",
        "digital": "0:11:37",
        "hours": 0,
        "minutes": 11,
        "name": "azure",
        "percent": 1.7,
        "seconds": 37,
        "text": "11 mins",
        "total_seconds": 697.640969
      },
      {
        "decimal": "0.07",
        "digital": "0:04:33",
        "hours": 0,
        "minutes": 4,
        "name": "folder.service",
        "percent": 0.67,
        "seconds": 33,
        "text": "4 mins",
        "total_seconds": 273.347119
      },
      {
        "decimal": "0.07",
        "digital": "0:04:33",
        "hours": 0,
        "minutes": 4,
        "name": "dialog",
        "percent": 0.67,
        "seconds": 33,
        "text": "4 mins",
        "total_seconds": 273.347119
      },
      {
        "decimal": "0.07",
        "digital": "0:04:33",
        "hours": 0,
        "minutes": 4,
        "name": "keycodes",
        "percent": 0.67,
        "seconds": 33,
        "text": "4 mins",
        "total_seconds": 273.347119
      },
      {
        "decimal": "0.07",
        "digital": "0:04:33",
        "hours": 0,
        "minutes": 4,
        "name": "chips",
        "percent": 0.67,
        "seconds": 33,
        "text": "4 mins",
        "total_seconds": 273.347119
      },
      {
        "decimal": "0.07",
        "digital": "0:04:33",
        "hours": 0,
        "minutes": 4,
        "name": "forms",
        "percent": 0.67,
        "seconds": 33,
        "text": "4 mins",
        "total_seconds": 273.347119
      },
      {
        "decimal": "0.07",
        "digital": "0:04:33",
        "hours": 0,
        "minutes": 4,
        "name": "collections",
        "percent": 0.67,
        "seconds": 33,
        "text": "4 mins",
        "total_seconds": 273.347119
      },
      {
        "decimal": "0.05",
        "digital": "0:03:45",
        "hours": 0,
        "minutes": 3,
        "name": "mongoose",
        "percent": 0.55,
        "seconds": 45,
        "text": "3 mins",
        "total_seconds": 225.577551
      },
      {
        "decimal": "0.00",
        "digital": "0:00:17",
        "hours": 0,
        "minutes": 0,
        "name": "vega",
        "percent": 0.04,
        "seconds": 17,
        "text": "17 secs",
        "total_seconds": 17.832285
      },
      {
        "decimal": "0.00",
        "digital": "0:00:17",
        "hours": 0,
        "minutes": 0,
        "name": "lineChart",
        "percent": 0.04,
        "seconds": 17,
        "text": "17 secs",
        "total_seconds": 17.832285
      },
      {
        "decimal": "0.00",
        "digital": "0:00:17",
        "hours": 0,
        "minutes": 0,
        "name": "horizontalBarChart",
        "percent": 0.04,
        "seconds": 17,
        "text": "17 secs",
        "total_seconds": 17.832285
      },
      {
        "decimal": "0.00",
        "digital": "0:00:17",
        "hours": 0,
        "minutes": 0,
        "name": "type",
        "percent": 0.04,
        "seconds": 17,
        "text": "17 secs",
        "total_seconds": 17.832285
      },
      {
        "decimal": "0.00",
        "digital": "0:00:10",
        "hours": 0,
        "minutes": 0,
        "name": "analytics",
        "percent": 0.03,
        "seconds": 10,
        "text": "10 secs",
        "total_seconds": 10.664396
      },
      {
        "decimal": "0.00",
        "digital": "0:00:10",
        "hours": 0,
        "minutes": 0,
        "name": "ai",
        "percent": 0.03,
        "seconds": 10,
        "text": "10 secs",
        "total_seconds": 10.664396
      },
      {
        "decimal": "0.00",
        "digital": "0:00:10",
        "hours": 0,
        "minutes": 0,
        "name": "config",
        "percent": 0.02,
        "seconds": 10,
        "text": "10 secs",
        "total_seconds": 10.0487
      },
      {
        "decimal": "0.00",
        "digital": "0:00:06",
        "hours": 0,
        "minutes": 0,
        "name": "mailer",
        "percent": 0.01,
        "seconds": 6,
        "text": "6 secs",
        "total_seconds": 6.043486
      },
      {
        "decimal": "0.00",
        "digital": "0:00:04",
        "hours": 0,
        "minutes": 0,
        "name": "aws",
        "percent": 0.01,
        "seconds": 4,
        "text": "4 secs",
        "total_seconds": 4.095042
      },
      {
        "decimal": "0.00",
        "digital": "0:00:04",
        "hours": 0,
        "minutes": 0,
        "name": "recorder",
        "percent": 0.01,
        "seconds": 4,
        "text": "4 secs",
        "total_seconds": 4.095042
      },
      {
        "decimal": "0.00",
        "digital": "0:00:04",
        "hours": 0,
        "minutes": 0,
        "name": "csv",
        "percent": 0.01,
        "seconds": 4,
        "text": "4 secs",
        "total_seconds": 4.095042
      },
      {
        "decimal": "0.00",
        "digital": "0:00:04",
        "hours": 0,
        "minutes": 0,
        "name": "node-fetch",
        "percent": 0.01,
        "seconds": 4,
        "text": "4 secs",
        "total_seconds": 4.005214
      },
      {
        "decimal": "0.00",
        "digital": "0:00:02",
        "hours": 0,
        "minutes": 0,
        "name": "dateutil",
        "percent": 0.01,
        "seconds": 2,
        "text": "2 secs",
        "total_seconds": 2.336057
      },
      {
        "decimal": "0.00",
        "digital": "0:00:02",
        "hours": 0,
        "minutes": 0,
        "name": "bs4",
        "percent": 0.01,
        "seconds": 2,
        "text": "2 secs",
        "total_seconds": 2.336057
      },
      {
        "decimal": "0.00",
        "digital": "0:00:02",
        "hours": 0,
        "minutes": 0,
        "name": "flask_restful",
        "percent": 0.01,
        "seconds": 2,
        "text": "2 secs",
        "total_seconds": 2.336057
      },
      {
        "decimal": "0.00",
        "digital": "0:00:02",
        "hours": 0,
        "minutes": 0,
        "name": "json",
        "percent": 0.01,
        "seconds": 2,
        "text": "2 secs",
        "total_seconds": 2.336057
      },
      {
        "decimal": "0.00",
        "digital": "0:00:02",
        "hours": 0,
        "minutes": 0,
        "name": "lxml",
        "percent": 0.01,
        "seconds": 2,
        "text": "2 secs",
        "total_seconds": 2.336057
      },
      {
        "decimal": "0.00",
        "digital": "0:00:02",
        "hours": 0,
        "minutes": 0,
        "name": "logging",
        "percent": 0.01,
        "seconds": 2,
        "text": "2 secs",
        "total_seconds": 2.336057
      },
      {
        "decimal": "0.00",
        "digital": "0:00:02",
        "hours": 0,
        "minutes": 0,
        "name": "flask",
        "percent": 0.01,
        "seconds": 2,
        "text": "2 secs",
        "total_seconds": 2.336057
      },
      {
        "decimal": "0.00",
        "digital": "0:00:01",
        "hours": 0,
        "minutes": 0,
        "name": "activecampaign",
        "percent": 0,
        "seconds": 1,
        "text": "1 sec",
        "total_seconds": 1.948444
      },
      {
        "decimal": "0.00",
        "digital": "0:00:01",
        "hours": 0,
        "minutes": 0,
        "name": "crypto",
        "percent": 0,
        "seconds": 1,
        "text": "1 sec",
        "total_seconds": 1.948444
      },
      {
        "decimal": "0.00",
        "digital": "0:00:01",
        "hours": 0,
        "minutes": 0,
        "name": "generate-password",
        "percent": 0,
        "seconds": 1,
        "text": "1 sec",
        "total_seconds": 1.948444
      },
      {
        "decimal": "0.00",
        "digital": "0:00:01",
        "hours": 0,
        "minutes": 0,
        "name": "bcryptjs",
        "percent": 0,
        "seconds": 1,
        "text": "1 sec",
        "total_seconds": 1.948444
      },
      {
        "decimal": "0.00",
        "digital": "0:00:01",
        "hours": 0,
        "minutes": 0,
        "name": "sendgrid",
        "percent": 0,
        "seconds": 1,
        "text": "1 sec",
        "total_seconds": 1.948444
      },
      {
        "decimal": "0.00",
        "digital": "0:00:01",
        "hours": 0,
        "minutes": 0,
        "name": "subscription",
        "percent": 0,
        "seconds": 1,
        "text": "1 sec",
        "total_seconds": 1.948444
      },
      {
        "decimal": "0.00",
        "digital": "0:00:00",
        "hours": 0,
        "minutes": 0,
        "name": "constant",
        "percent": 0,
        "seconds": 0,
        "text": "0 secs",
        "total_seconds": 0
      },
      {
        "decimal": "0.00",
        "digital": "0:00:00",
        "hours": 0,
        "minutes": 0,
        "name": "amazon-s3-uri",
        "percent": 0,
        "seconds": 0,
        "text": "0 secs",
        "total_seconds": 0
      },
      {
        "decimal": "0.00",
        "digital": "0:00:00",
        "hours": 0,
        "minutes": 0,
        "name": "aws-sdk",
        "percent": 0,
        "seconds": 0,
        "text": "0 secs",
        "total_seconds": 0
      },
      {
        "decimal": "0.00",
        "digital": "0:00:00",
        "hours": 0,
        "minutes": 0,
        "name": "multer-s3",
        "percent": 0,
        "seconds": 0,
        "text": "0 secs",
        "total_seconds": 0
      },
      {
        "decimal": "0.00",
        "digital": "0:00:00",
        "hours": 0,
        "minutes": 0,
        "name": "multer",
        "percent": 0,
        "seconds": 0,
        "text": "0 secs",
        "total_seconds": 0
      },
      {
        "decimal": "0.00",
        "digital": "0:00:00",
        "hours": 0,
        "minutes": 0,
        "name": "en_core_web_lg",
        "percent": 0,
        "seconds": 0,
        "text": "0 secs",
        "total_seconds": 0
      },
      {
        "decimal": "0.00",
        "digital": "0:00:00",
        "hours": 0,
        "minutes": 0,
        "name": "re",
        "percent": 0,
        "seconds": 0,
        "text": "0 secs",
        "total_seconds": 0
      },
      {
        "decimal": "0.00",
        "digital": "0:00:00",
        "hours": 0,
        "minutes": 0,
        "name": "nltk",
        "percent": 0,
        "seconds": 0,
        "text": "0 secs",
        "total_seconds": 0
      }
    ],
    "editors": [
      {
        "decimal": "1.35",
        "digital": "1:21:39",
        "hours": 1,
        "minutes": 21,
        "name": "VS Code",
        "percent": 100,
        "seconds": 39,
        "text": "1 hr 21 mins",
        "total_seconds": 4899.098756
      }
    ],
    "grand_total": {
      "decimal": "1.35",
      "digital": "1:21",
      "hours": 1,
      "minutes": 21,
      "text": "1 hr 21 mins",
      "total_seconds": 4899.098756
    },
    "languages": [
      {
        "decimal": "1.10",
        "digital": "1:06:02",
        "hours": 1,
        "minutes": 6,
        "name": "TypeScript",
        "percent": 80.88,
        "seconds": 2,
        "text": "1 hr 6 mins",
        "total_seconds": 3962.621734
      },
      {
        "decimal": "0.23",
        "digital": "0:14:55",
        "hours": 0,
        "minutes": 14,
        "name": "HTML",
        "percent": 18.28,
        "seconds": 55,
        "text": "14 mins",
        "total_seconds": 895.369417
      },
      {
        "decimal": "0.00",
        "digital": "0:00:38",
        "hours": 0,
        "minutes": 0,
        "name": "Bash",
        "percent": 0.79,
        "seconds": 38,
        "text": "38 secs",
        "total_seconds": 38.771548
      },
      {
        "decimal": "0.00",
        "digital": "0:00:02",
        "hours": 0,
        "minutes": 0,
        "name": "Python",
        "percent": 0.05,
        "seconds": 2,
        "text": "2 secs",
        "total_seconds": 2.336057
      }
    ],
    "machines": [
      {
        "decimal": "1.35",
        "digital": "1:21:39",
        "hours": 1,
        "machine_name_id": "61db558b-4cae-4d1b-ab2a-6558cba583e0",
        "minutes": 21,
        "name": "Vatsal",
        "percent": 100,
        "seconds": 39,
        "text": "1 hr 21 mins",
        "total_seconds": 4899.098756
      }
    ],
    "operating_systems": [
      {
        "decimal": "1.35",
        "digital": "1:21:39",
        "hours": 1,
        "minutes": 21,
        "name": "Windows",
        "percent": 100,
        "seconds": 39,
        "text": "1 hr 21 mins",
        "total_seconds": 4899.098756
      }
    ],
    "projects": [
      {
        "decimal": "0.57",
        "digital": "0:34:17",
        "hours": 0,
        "minutes": 34,
        "name": "speak-server",
        "percent": 42.01,
        "seconds": 17,
        "text": "34 mins",
        "total_seconds": 2057.881757
      },
      {
        "decimal": "0.50",
        "digital": "0:30:04",
        "hours": 0,
        "minutes": 30,
        "name": "speak-media-library",
        "percent": 36.83,
        "seconds": 4,
        "text": "30 mins",
        "total_seconds": 1804.57155
      },
      {
        "decimal": "0.28",
        "digital": "0:17:14",
        "hours": 0,
        "minutes": 17,
        "name": "speak-client",
        "percent": 21.11,
        "seconds": 14,
        "text": "17 mins",
        "total_seconds": 1034.309392
      },
      {
        "decimal": "0.00",
        "digital": "0:00:02",
        "hours": 0,
        "minutes": 0,
        "name": "speak-ai-middleware",
        "percent": 0.05,
        "seconds": 2,
        "text": "2 secs",
        "total_seconds": 2.336057
      }
    ],
    "range": {
      "date": "2022-02-01",
      "end": "2022-02-02T04:59:59Z",
      "start": "2022-02-01T05:00:00Z",
      "text": "Yesterday",
      "timezone": "America/Toronto"
    }
  }
]