[
  {
    "summary_date": "2022-02-28",
    "period_id": 2,
    "is_longest": 1,
    "timezone": 330,
    "bedtime_end": "2022-03-01T10:30:27+05:30",
    "bedtime_start": "2022-03-01T01:22:27+05:30",
    "breath_average": 12.5,
    "duration": 32880,
    "total": 27120,
    "awake": 5760,
    "rem": 4950,
    "deep": 8310,
    "light": 13860,
    "midpoint_time": 15900,
    "efficiency": 82,
    "restless": 39,
    "onset_latency": 780,
    "hr_5min": [
      63,
      63,
      63,
      61,
      59,
      59,
      60,
      60,
      60,
      60,
      65,
      61,
      61,
      65,
      64,
      62,
      65,
      63,
      63,
      64,
      61,
      61,
      59,
      59,
      60,
      60,
      60,
      61,
      62,
      60,
      59,
      60,
      60,
      59,
      59,
      60,
      60,
      60,
      60,
      59,
      59,
      67,
      67,
      65,
      61,
      57,
      62,
      64,
      65,
      59,
      59,
      59,
      58,
      60,
      59,
      0,
      58,
      59,
      59,
      59,
      60,
      60,
      61,
      60,
      64,
      64,
      64,
      65,
      61,
      61,
      65,
      63,
      66,
      66,
      60,
      61,
      60,
      60,
      60,
      60,
      60,
      60,
      61,
      59,
      61,
      65,
      64,
      63,
      61,
      60,
      65,
      61,
      60,
      60,
      60,
      61,
      61,
      61,
      61,
      61,
      61,
      63,
      65,
      62,
      64,
      64,
      65,
      68,
      75,
      0
    ],
    "hr_average": 61.56,
    "hr_lowest": 57,
    "hypnogram_5min": "22222111111222222232222211133222422111112333334424222224211111113333222344222221111223333242222222221133443444",
    "rmssd": 36,
    "rmssd_5min": [
      33,
      37,
      37,
      40,
      32,
      32,
      30,
      31,
      31,
      31,
      47,
      43,
      31,
      40,
      46,
      41,
      41,
      31,
      30,
      34,
      25,
      33,
      34,
      25,
      40,
      30,
      36,
      44,
      43,
      30,
      29,
      33,
      40,
      38,
      33,
      34,
      41,
      35,
      36,
      44,
      49,
      28,
      29,
      31,
      33,
      45,
      28,
      26,
      38,
      30,
      26,
      28,
      40,
      39,
      32,
      0,
      31,
      34,
      33,
      33,
      28,
      29,
      34,
      48,
      41,
      45,
      31,
      42,
      45,
      43,
      31,
      29,
      41,
      28,
      35,
      52,
      52,
      46,
      44,
      46,
      47,
      45,
      40,
      41,
      32,
      46,
      28,
      47,
      46,
      44,
      33,
      28,
      37,
      35,
      28,
      36,
      28,
      34,
      31,
      28,
      28,
      35,
      45,
      39,
      41,
      36,
      39,
      37,
      32,
      0
    ],
    "score": 72,
    "score_alignment": 21,
    "score_deep": 99,
    "score_disturbances": 54,
    "score_efficiency": 76,
    "score_latency": 94,
    "score_rem": 68,
    "score_total": 79,
    "temperature_deviation": -0.04,
    "temperature_trend_deviation": 0.03,
    "bedtime_start_delta": 4947,
    "bedtime_end_delta": 37827,
    "midpoint_at_delta": 20847,
    "temperature_delta": -0.04
  }
]