[
  {
    "categories": [
      {
        "decimal": "3.85",
        "digital": "3:51:19",
        "hours": 3,
        "minutes": 51,
        "name": "Coding",
        "percent": 100,
        "seconds": 19,
        "text": "3 hrs 51 mins",
        "total_seconds": 13879.948876
      }
    ],
    "dependencies": [
      {
        "decimal": "1.15",
        "digital": "1:09:02",
        "hours": 1,
        "minutes": 9,
        "name": "core",
        "percent": 6.79,
        "seconds": 2,
        "text": "1 hr 9 mins",
        "total_seconds": 4142.610527
      },
      {
        "decimal": "1.10",
        "digital": "1:06:55",
        "hours": 1,
        "minutes": 6,
        "name": "auth",
        "percent": 6.58,
        "seconds": 55,
        "text": "1 hr 6 mins",
        "total_seconds": 4015.982458
      },
      {
        "decimal": "1.10",
        "digital": "1:06:47",
        "hours": 1,
        "minutes": 6,
        "name": "lodash",
        "percent": 6.57,
        "seconds": 47,
        "text": "1 hr 6 mins",
        "total_seconds": 4007.77942
      },
      {
        "decimal": "0.85",
        "digital": "0:51:24",
        "hours": 0,
        "minutes": 51,
        "name": "services",
        "percent": 5.05,
        "seconds": 24,
        "text": "51 mins",
        "total_seconds": 3084.203111
      },
      {
        "decimal": "0.83",
        "digital": "0:50:00",
        "hours": 0,
        "minutes": 50,
        "name": "rxjs",
        "percent": 4.92,
        "seconds": 0,
        "text": "50 mins",
        "total_seconds": 3000.240536
      },
      {
        "decimal": "0.80",
        "digital": "0:48:55",
        "hours": 0,
        "minutes": 48,
        "name": "types",
        "percent": 4.81,
        "seconds": 55,
        "text": "48 mins",
        "total_seconds": 2935.882073
      },
      {
        "decimal": "0.80",
        "digital": "0:48:43",
        "hours": 0,
        "minutes": 48,
        "name": "router",
        "percent": 4.79,
        "seconds": 43,
        "text": "48 mins",
        "total_seconds": 2923.78782
      },
      {
        "decimal": "0.77",
        "digital": "0:46:54",
        "hours": 0,
        "minutes": 46,
        "name": "store",
        "percent": 4.61,
        "seconds": 54,
        "text": "46 mins",
        "total_seconds": 2814.782833
      },
      {
        "decimal": "0.77",
        "digital": "0:46:36",
        "hours": 0,
        "minutes": 46,
        "name": "reducers",
        "percent": 4.58,
        "seconds": 36,
        "text": "46 mins",
        "total_seconds": 2796.333351
      },
      {
        "decimal": "0.60",
        "digital": "0:36:33",
        "hours": 0,
        "minutes": 36,
        "name": "platform-browser",
        "percent": 3.59,
        "seconds": 33,
        "text": "36 mins",
        "total_seconds": 2193.553949
      },
      {
        "decimal": "0.60",
        "digital": "0:36:16",
        "hours": 0,
        "minutes": 36,
        "name": "forms",
        "percent": 3.57,
        "seconds": 16,
        "text": "36 mins",
        "total_seconds": 2176.112751
      },
      {
        "decimal": "0.57",
        "digital": "0:34:44",
        "hours": 0,
        "minutes": 34,
        "name": "amplitude.service",
        "percent": 3.42,
        "seconds": 44,
        "text": "34 mins",
        "total_seconds": 2084.197824
      },
      {
        "decimal": "0.53",
        "digital": "0:32:41",
        "hours": 0,
        "minutes": 32,
        "name": "dialog",
        "percent": 3.22,
        "seconds": 41,
        "text": "32 mins",
        "total_seconds": 1961.847998
      },
      {
        "decimal": "0.37",
        "digital": "0:22:40",
        "hours": 0,
        "minutes": 22,
        "name": "logger",
        "percent": 2.23,
        "seconds": 40,
        "text": "22 mins",
        "total_seconds": 1360.01998
      },
      {
        "decimal": "0.28",
        "digital": "0:17:17",
        "hours": 0,
        "minutes": 17,
        "name": "interfaces",
        "percent": 1.7,
        "seconds": 17,
        "text": "17 mins",
        "total_seconds": 1037.559712
      },
      {
        "decimal": "0.27",
        "digital": "0:16:39",
        "hours": 0,
        "minutes": 16,
        "name": "environment",
        "percent": 1.64,
        "seconds": 39,
        "text": "16 mins",
        "total_seconds": 999.324475
      },
      {
        "decimal": "0.23",
        "digital": "0:14:59",
        "hours": 0,
        "minutes": 14,
        "name": "layout.config",
        "percent": 1.47,
        "seconds": 59,
        "text": "14 mins",
        "total_seconds": 899.316237
      },
      {
        "decimal": "0.23",
        "digital": "0:14:23",
        "hours": 0,
        "minutes": 14,
        "name": "amplitude-js",
        "percent": 1.41,
        "seconds": 23,
        "text": "14 mins",
        "total_seconds": 863.035614
      },
      {
        "decimal": "0.22",
        "digital": "0:13:42",
        "hours": 0,
        "minutes": 13,
        "name": "object-path",
        "percent": 1.35,
        "seconds": 42,
        "text": "13 mins",
        "total_seconds": 822.433896
      },
      {
        "decimal": "0.22",
        "digital": "0:13:42",
        "hours": 0,
        "minutes": 13,
        "name": "menu.config",
        "percent": 1.35,
        "seconds": 42,
        "text": "13 mins",
        "total_seconds": 822.433896
      },
      {
        "decimal": "0.22",
        "digital": "0:13:42",
        "hours": 0,
        "minutes": 13,
        "name": "folder.service",
        "percent": 1.35,
        "seconds": 42,
        "text": "13 mins",
        "total_seconds": 822.433896
      },
      {
        "decimal": "0.22",
        "digital": "0:13:42",
        "hours": 0,
        "minutes": 13,
        "name": "html-class.service",
        "percent": 1.35,
        "seconds": 42,
        "text": "13 mins",
        "total_seconds": 822.433896
      },
      {
        "decimal": "0.20",
        "digital": "0:12:05",
        "hours": 0,
        "minutes": 12,
        "name": "model",
        "percent": 1.19,
        "seconds": 5,
        "text": "12 mins",
        "total_seconds": 725.310688
      },
      {
        "decimal": "0.13",
        "digital": "0:08:31",
        "hours": 0,
        "minutes": 8,
        "name": "express",
        "percent": 0.84,
        "seconds": 31,
        "text": "8 mins",
        "total_seconds": 511.153507
      },
      {
        "decimal": "0.12",
        "digital": "0:07:18",
        "hours": 0,
        "minutes": 7,
        "name": "utils",
        "percent": 0.72,
        "seconds": 18,
        "text": "7 mins",
        "total_seconds": 438.290213
      },
      {
        "decimal": "0.12",
        "digital": "0:07:13",
        "hours": 0,
        "minutes": 7,
        "name": "media",
        "percent": 0.71,
        "seconds": 13,
        "text": "7 mins",
        "total_seconds": 433.704708
      },
      {
        "decimal": "0.10",
        "digital": "0:06:44",
        "hours": 0,
        "minutes": 6,
        "name": "config",
        "percent": 0.66,
        "seconds": 44,
        "text": "6 mins",
        "total_seconds": 404.044074
      },
      {
        "decimal": "0.08",
        "digital": "0:05:57",
        "hours": 0,
        "minutes": 5,
        "name": "mailer",
        "percent": 0.59,
        "seconds": 57,
        "text": "5 mins",
        "total_seconds": 357.152141
      },
      {
        "decimal": "0.08",
        "digital": "0:05:54",
        "hours": 0,
        "minutes": 5,
        "name": "cluster",
        "percent": 0.58,
        "seconds": 54,
        "text": "5 mins",
        "total_seconds": 354.588323
      },
      {
        "decimal": "0.08",
        "digital": "0:05:46",
        "hours": 0,
        "minutes": 5,
        "name": "cors",
        "percent": 0.57,
        "seconds": 46,
        "text": "5 mins",
        "total_seconds": 346.745066
      },
      {
        "decimal": "0.08",
        "digital": "0:05:46",
        "hours": 0,
        "minutes": 5,
        "name": "cookie-parser",
        "percent": 0.57,
        "seconds": 46,
        "text": "5 mins",
        "total_seconds": 346.745066
      },
      {
        "decimal": "0.08",
        "digital": "0:05:46",
        "hours": 0,
        "minutes": 5,
        "name": "express-mongo-sanitize",
        "percent": 0.57,
        "seconds": 46,
        "text": "5 mins",
        "total_seconds": 346.745066
      },
      {
        "decimal": "0.08",
        "digital": "0:05:46",
        "hours": 0,
        "minutes": 5,
        "name": "register",
        "percent": 0.57,
        "seconds": 46,
        "text": "5 mins",
        "total_seconds": 346.745066
      },
      {
        "decimal": "0.08",
        "digital": "0:05:46",
        "hours": 0,
        "minutes": 5,
        "name": "path",
        "percent": 0.57,
        "seconds": 46,
        "text": "5 mins",
        "total_seconds": 346.745066
      },
      {
        "decimal": "0.08",
        "digital": "0:05:46",
        "hours": 0,
        "minutes": 5,
        "name": "express-request-id",
        "percent": 0.57,
        "seconds": 46,
        "text": "5 mins",
        "total_seconds": 346.745066
      },
      {
        "decimal": "0.08",
        "digital": "0:05:46",
        "hours": 0,
        "minutes": 5,
        "name": "morgan",
        "percent": 0.57,
        "seconds": 46,
        "text": "5 mins",
        "total_seconds": 346.745066
      },
      {
        "decimal": "0.08",
        "digital": "0:05:46",
        "hours": 0,
        "minutes": 5,
        "name": "routes",
        "percent": 0.57,
        "seconds": 46,
        "text": "5 mins",
        "total_seconds": 346.745066
      },
      {
        "decimal": "0.08",
        "digital": "0:05:46",
        "hours": 0,
        "minutes": 5,
        "name": "helmet",
        "percent": 0.57,
        "seconds": 46,
        "text": "5 mins",
        "total_seconds": 346.745066
      },
      {
        "decimal": "0.08",
        "digital": "0:05:46",
        "hours": 0,
        "minutes": 5,
        "name": "os",
        "percent": 0.57,
        "seconds": 46,
        "text": "5 mins",
        "total_seconds": 346.745066
      },
      {
        "decimal": "0.08",
        "digital": "0:05:46",
        "hours": 0,
        "minutes": 5,
        "name": "database",
        "percent": 0.57,
        "seconds": 46,
        "text": "5 mins",
        "total_seconds": 346.745066
      },
      {
        "decimal": "0.08",
        "digital": "0:05:46",
        "hours": 0,
        "minutes": 5,
        "name": "middleware",
        "percent": 0.57,
        "seconds": 46,
        "text": "5 mins",
        "total_seconds": 346.745066
      },
      {
        "decimal": "0.08",
        "digital": "0:05:46",
        "hours": 0,
        "minutes": 5,
        "name": "dotenv",
        "percent": 0.57,
        "seconds": 46,
        "text": "5 mins",
        "total_seconds": 346.745066
      },
      {
        "decimal": "0.08",
        "digital": "0:05:46",
        "hours": 0,
        "minutes": 5,
        "name": "morgan-json",
        "percent": 0.57,
        "seconds": 46,
        "text": "5 mins",
        "total_seconds": 346.745066
      },
      {
        "decimal": "0.07",
        "digital": "0:04:33",
        "hours": 0,
        "minutes": 4,
        "name": "meta",
        "percent": 0.45,
        "seconds": 33,
        "text": "4 mins",
        "total_seconds": 273.204777
      },
      {
        "decimal": "0.07",
        "digital": "0:04:31",
        "hours": 0,
        "minutes": 4,
        "name": "canvas",
        "percent": 0.44,
        "seconds": 31,
        "text": "4 mins",
        "total_seconds": 271.479301
      },
      {
        "decimal": "0.07",
        "digital": "0:04:31",
        "hours": 0,
        "minutes": 4,
        "name": ".",
        "percent": 0.44,
        "seconds": 31,
        "text": "4 mins",
        "total_seconds": 271.479301
      },
      {
        "decimal": "0.07",
        "digital": "0:04:31",
        "hours": 0,
        "minutes": 4,
        "name": "index",
        "percent": 0.44,
        "seconds": 31,
        "text": "4 mins",
        "total_seconds": 271.479301
      },
      {
        "decimal": "0.07",
        "digital": "0:04:31",
        "hours": 0,
        "minutes": 4,
        "name": "transcription",
        "percent": 0.44,
        "seconds": 31,
        "text": "4 mins",
        "total_seconds": 271.479301
      },
      {
        "decimal": "0.05",
        "digital": "0:03:30",
        "hours": 0,
        "minutes": 3,
        "name": "core.module",
        "percent": 0.35,
        "seconds": 30,
        "text": "3 mins",
        "total_seconds": 210.726044
      },
      {
        "decimal": "0.05",
        "digital": "0:03:23",
        "hours": 0,
        "minutes": 3,
        "name": "bcryptjs",
        "percent": 0.33,
        "seconds": 23,
        "text": "3 mins",
        "total_seconds": 203.840727
      },
      {
        "decimal": "0.05",
        "digital": "0:03:19",
        "hours": 0,
        "minutes": 3,
        "name": "shared.module",
        "percent": 0.33,
        "seconds": 19,
        "text": "3 mins",
        "total_seconds": 199.948765
      },
      {
        "decimal": "0.05",
        "digital": "0:03:02",
        "hours": 0,
        "minutes": 3,
        "name": "http",
        "percent": 0.3,
        "seconds": 2,
        "text": "3 mins",
        "total_seconds": 182.548777
      },
      {
        "decimal": "0.03",
        "digital": "0:02:58",
        "hours": 0,
        "minutes": 2,
        "name": "enum",
        "percent": 0.29,
        "seconds": 58,
        "text": "2 mins",
        "total_seconds": 178.677516
      },
      {
        "decimal": "0.03",
        "digital": "0:02:43",
        "hours": 0,
        "minutes": 2,
        "name": "templates",
        "percent": 0.27,
        "seconds": 43,
        "text": "2 mins",
        "total_seconds": 163.323836
      },
      {
        "decimal": "0.03",
        "digital": "0:02:43",
        "hours": 0,
        "minutes": 2,
        "name": "responses",
        "percent": 0.27,
        "seconds": 43,
        "text": "2 mins",
        "total_seconds": 163.323836
      },
      {
        "decimal": "0.03",
        "digital": "0:02:43",
        "hours": 0,
        "minutes": 2,
        "name": "notification",
        "percent": 0.27,
        "seconds": 43,
        "text": "2 mins",
        "total_seconds": 163.323836
      },
      {
        "decimal": "0.03",
        "digital": "0:02:43",
        "hours": 0,
        "minutes": 2,
        "name": "activecampaign",
        "percent": 0.27,
        "seconds": 43,
        "text": "2 mins",
        "total_seconds": 163.323836
      },
      {
        "decimal": "0.03",
        "digital": "0:02:37",
        "hours": 0,
        "minutes": 2,
        "name": "stripe",
        "percent": 0.26,
        "seconds": 37,
        "text": "2 mins",
        "total_seconds": 157.571084
      },
      {
        "decimal": "0.03",
        "digital": "0:02:37",
        "hours": 0,
        "minutes": 2,
        "name": "aws",
        "percent": 0.26,
        "seconds": 37,
        "text": "2 mins",
        "total_seconds": 157.571084
      },
      {
        "decimal": "0.03",
        "digital": "0:02:37",
        "hours": 0,
        "minutes": 2,
        "name": "insightCategories",
        "percent": 0.26,
        "seconds": 37,
        "text": "2 mins",
        "total_seconds": 157.571084
      },
      {
        "decimal": "0.03",
        "digital": "0:02:13",
        "hours": 0,
        "minutes": 2,
        "name": "common",
        "percent": 0.22,
        "seconds": 13,
        "text": "2 mins",
        "total_seconds": 133.843703
      },
      {
        "decimal": "0.03",
        "digital": "0:02:03",
        "hours": 0,
        "minutes": 2,
        "name": "onboarding-survey.component",
        "percent": 0.2,
        "seconds": 3,
        "text": "2 mins",
        "total_seconds": 123.401567
      },
      {
        "decimal": "0.02",
        "digital": "0:01:54",
        "hours": 0,
        "minutes": 1,
        "name": "operators",
        "percent": 0.19,
        "seconds": 54,
        "text": "1 min",
        "total_seconds": 114.710988
      },
      {
        "decimal": "0.02",
        "digital": "0:01:53",
        "hours": 0,
        "minutes": 1,
        "name": "auth.module",
        "percent": 0.19,
        "seconds": 53,
        "text": "1 min",
        "total_seconds": 113.605026
      },
      {
        "decimal": "0.02",
        "digital": "0:01:27",
        "hours": 0,
        "minutes": 1,
        "name": "ngx-perfect-scrollbar",
        "percent": 0.14,
        "seconds": 27,
        "text": "1 min",
        "total_seconds": 87.65962
      },
      {
        "decimal": "0.02",
        "digital": "0:01:26",
        "hours": 0,
        "minutes": 1,
        "name": "effects",
        "percent": 0.14,
        "seconds": 26,
        "text": "1 min",
        "total_seconds": 86.125968
      },
      {
        "decimal": "0.02",
        "digital": "0:01:16",
        "hours": 0,
        "minutes": 1,
        "name": "app.component",
        "percent": 0.13,
        "seconds": 16,
        "text": "1 min",
        "total_seconds": 76.882341
      },
      {
        "decimal": "0.02",
        "digital": "0:01:16",
        "hours": 0,
        "minutes": 1,
        "name": "overlay",
        "percent": 0.13,
        "seconds": 16,
        "text": "1 min",
        "total_seconds": 76.882341
      },
      {
        "decimal": "0.02",
        "digital": "0:01:16",
        "hours": 0,
        "minutes": 1,
        "name": "router-store",
        "percent": 0.13,
        "seconds": 16,
        "text": "1 min",
        "total_seconds": 76.882341
      },
      {
        "decimal": "0.02",
        "digital": "0:01:16",
        "hours": 0,
        "minutes": 1,
        "name": "logrocket",
        "percent": 0.13,
        "seconds": 16,
        "text": "1 min",
        "total_seconds": 76.882341
      },
      {
        "decimal": "0.02",
        "digital": "0:01:16",
        "hours": 0,
        "minutes": 1,
        "name": "app-routing.module",
        "percent": 0.13,
        "seconds": 16,
        "text": "1 min",
        "total_seconds": 76.882341
      },
      {
        "decimal": "0.02",
        "digital": "0:01:16",
        "hours": 0,
        "minutes": 1,
        "name": "store-devtools",
        "percent": 0.13,
        "seconds": 16,
        "text": "1 min",
        "total_seconds": 76.882341
      },
      {
        "decimal": "0.02",
        "digital": "0:01:16",
        "hours": 0,
        "minutes": 1,
        "name": "theme.module",
        "percent": 0.13,
        "seconds": 16,
        "text": "1 min",
        "total_seconds": 76.882341
      },
      {
        "decimal": "0.02",
        "digital": "0:01:16",
        "hours": 0,
        "minutes": 1,
        "name": "ng-inline-svg",
        "percent": 0.13,
        "seconds": 16,
        "text": "1 min",
        "total_seconds": 76.882341
      },
      {
        "decimal": "0.02",
        "digital": "0:01:16",
        "hours": 0,
        "minutes": 1,
        "name": "animations",
        "percent": 0.13,
        "seconds": 16,
        "text": "1 min",
        "total_seconds": 76.882341
      },
      {
        "decimal": "0.02",
        "digital": "0:01:02",
        "hours": 0,
        "minutes": 1,
        "name": "onboarding.module",
        "percent": 0.1,
        "seconds": 2,
        "text": "1 min",
        "total_seconds": 62.519525
      },
      {
        "decimal": "0.00",
        "digital": "0:00:47",
        "hours": 0,
        "minutes": 0,
        "name": "error-page.component",
        "percent": 0.08,
        "seconds": 47,
        "text": "47 secs",
        "total_seconds": 47.499964
      },
      {
        "decimal": "0.00",
        "digital": "0:00:46",
        "hours": 0,
        "minutes": 0,
        "name": "crypto",
        "percent": 0.08,
        "seconds": 46,
        "text": "46 secs",
        "total_seconds": 46.269643
      },
      {
        "decimal": "0.00",
        "digital": "0:00:42",
        "hours": 0,
        "minutes": 0,
        "name": "mongoose",
        "percent": 0.07,
        "seconds": 42,
        "text": "42 secs",
        "total_seconds": 42.242367
      },
      {
        "decimal": "0.00",
        "digital": "0:00:36",
        "hours": 0,
        "minutes": 0,
        "name": "notification.module",
        "percent": 0.06,
        "seconds": 36,
        "text": "36 secs",
        "total_seconds": 36.722685
      },
      {
        "decimal": "0.00",
        "digital": "0:00:36",
        "hours": 0,
        "minutes": 0,
        "name": "recorder.module",
        "percent": 0.06,
        "seconds": 36,
        "text": "36 secs",
        "total_seconds": 36.722685
      },
      {
        "decimal": "0.00",
        "digital": "0:00:36",
        "hours": 0,
        "minutes": 0,
        "name": "folder.module",
        "percent": 0.06,
        "seconds": 36,
        "text": "36 secs",
        "total_seconds": 36.722685
      },
      {
        "decimal": "0.00",
        "digital": "0:00:36",
        "hours": 0,
        "minutes": 0,
        "name": "pricing.module",
        "percent": 0.06,
        "seconds": 36,
        "text": "36 secs",
        "total_seconds": 36.722685
      },
      {
        "decimal": "0.00",
        "digital": "0:00:36",
        "hours": 0,
        "minutes": 0,
        "name": "user.module",
        "percent": 0.06,
        "seconds": 36,
        "text": "36 secs",
        "total_seconds": 36.722685
      },
      {
        "decimal": "0.00",
        "digital": "0:00:36",
        "hours": 0,
        "minutes": 0,
        "name": "user-admin.module",
        "percent": 0.06,
        "seconds": 36,
        "text": "36 secs",
        "total_seconds": 36.722685
      },
      {
        "decimal": "0.00",
        "digital": "0:00:36",
        "hours": 0,
        "minutes": 0,
        "name": "upload.module",
        "percent": 0.06,
        "seconds": 36,
        "text": "36 secs",
        "total_seconds": 36.722685
      },
      {
        "decimal": "0.00",
        "digital": "0:00:36",
        "hours": 0,
        "minutes": 0,
        "name": "insights-customization.module",
        "percent": 0.06,
        "seconds": 36,
        "text": "36 secs",
        "total_seconds": 36.722685
      },
      {
        "decimal": "0.00",
        "digital": "0:00:36",
        "hours": 0,
        "minutes": 0,
        "name": "base.component",
        "percent": 0.06,
        "seconds": 36,
        "text": "36 secs",
        "total_seconds": 36.722685
      },
      {
        "decimal": "0.00",
        "digital": "0:00:36",
        "hours": 0,
        "minutes": 0,
        "name": "developers.module",
        "percent": 0.06,
        "seconds": 36,
        "text": "36 secs",
        "total_seconds": 36.722685
      },
      {
        "decimal": "0.00",
        "digital": "0:00:36",
        "hours": 0,
        "minutes": 0,
        "name": "explore.module",
        "percent": 0.06,
        "seconds": 36,
        "text": "36 secs",
        "total_seconds": 36.722685
      },
      {
        "decimal": "0.00",
        "digital": "0:00:36",
        "hours": 0,
        "minutes": 0,
        "name": "embed-media.module",
        "percent": 0.06,
        "seconds": 36,
        "text": "36 secs",
        "total_seconds": 36.722685
      },
      {
        "decimal": "0.00",
        "digital": "0:00:36",
        "hours": 0,
        "minutes": 0,
        "name": "integrations.module",
        "percent": 0.06,
        "seconds": 36,
        "text": "36 secs",
        "total_seconds": 36.722685
      },
      {
        "decimal": "0.00",
        "digital": "0:00:36",
        "hours": 0,
        "minutes": 0,
        "name": "media.module",
        "percent": 0.06,
        "seconds": 36,
        "text": "36 secs",
        "total_seconds": 36.722685
      },
      {
        "decimal": "0.00",
        "digital": "0:00:36",
        "hours": 0,
        "minutes": 0,
        "name": "dashboard.module",
        "percent": 0.06,
        "seconds": 36,
        "text": "36 secs",
        "total_seconds": 36.722685
      },
      {
        "decimal": "0.00",
        "digital": "0:00:31",
        "hours": 0,
        "minutes": 0,
        "name": "moment",
        "percent": 0.05,
        "seconds": 31,
        "text": "31 secs",
        "total_seconds": 31.984948
      },
      {
        "decimal": "0.00",
        "digital": "0:00:31",
        "hours": 0,
        "minutes": 0,
        "name": "mail",
        "percent": 0.05,
        "seconds": 31,
        "text": "31 secs",
        "total_seconds": 31.708614
      },
      {
        "decimal": "0.00",
        "digital": "0:00:25",
        "hours": 0,
        "minutes": 0,
        "name": "import.service",
        "percent": 0.04,
        "seconds": 25,
        "text": "25 secs",
        "total_seconds": 25.824704
      },
      {
        "decimal": "0.00",
        "digital": "0:00:21",
        "hours": 0,
        "minutes": 0,
        "name": "auth.service",
        "percent": 0.04,
        "seconds": 21,
        "text": "21 secs",
        "total_seconds": 21.577873
      },
      {
        "decimal": "0.00",
        "digital": "0:00:19",
        "hours": 0,
        "minutes": 0,
        "name": "subscription",
        "percent": 0.03,
        "seconds": 19,
        "text": "19 secs",
        "total_seconds": 19.400254
      },
      {
        "decimal": "0.00",
        "digital": "0:00:16",
        "hours": 0,
        "minutes": 0,
        "name": "user.model",
        "percent": 0.03,
        "seconds": 16,
        "text": "16 secs",
        "total_seconds": 16.144938
      },
      {
        "decimal": "0.00",
        "digital": "0:00:14",
        "hours": 0,
        "minutes": 0,
        "name": "ng-bootstrap",
        "percent": 0.02,
        "seconds": 14,
        "text": "14 secs",
        "total_seconds": 14.145971
      },
      {
        "decimal": "0.00",
        "digital": "0:00:11",
        "hours": 0,
        "minutes": 0,
        "name": "layout-utils.service",
        "percent": 0.02,
        "seconds": 11,
        "text": "11 secs",
        "total_seconds": 11.477034
      },
      {
        "decimal": "0.00",
        "digital": "0:00:10",
        "hours": 0,
        "minutes": 0,
        "name": "modal",
        "percent": 0.02,
        "seconds": 10,
        "text": "10 secs",
        "total_seconds": 10.777279
      },
      {
        "decimal": "0.00",
        "digital": "0:00:10",
        "hours": 0,
        "minutes": 0,
        "name": "chrome",
        "percent": 0.02,
        "seconds": 10,
        "text": "10 secs",
        "total_seconds": 10.777279
      },
      {
        "decimal": "0.00",
        "digital": "0:00:10",
        "hours": 0,
        "minutes": 0,
        "name": "ng2-google-charts",
        "percent": 0.02,
        "seconds": 10,
        "text": "10 secs",
        "total_seconds": 10.777279
      },
      {
        "decimal": "0.00",
        "digital": "0:00:10",
        "hours": 0,
        "minutes": 0,
        "name": "clipboard",
        "percent": 0.02,
        "seconds": 10,
        "text": "10 secs",
        "total_seconds": 10.777279
      },
      {
        "decimal": "0.00",
        "digital": "0:00:10",
        "hours": 0,
        "minutes": 0,
        "name": "image-selector.component",
        "percent": 0.02,
        "seconds": 10,
        "text": "10 secs",
        "total_seconds": 10.777279
      },
      {
        "decimal": "0.00",
        "digital": "0:00:10",
        "hours": 0,
        "minutes": 0,
        "name": "share-wordpress.component",
        "percent": 0.02,
        "seconds": 10,
        "text": "10 secs",
        "total_seconds": 10.777279
      },
      {
        "decimal": "0.00",
        "digital": "0:00:10",
        "hours": 0,
        "minutes": 0,
        "name": "document-recurrence.component",
        "percent": 0.02,
        "seconds": 10,
        "text": "10 secs",
        "total_seconds": 10.777279
      },
      {
        "decimal": "0.00",
        "digital": "0:00:10",
        "hours": 0,
        "minutes": 0,
        "name": "material.module",
        "percent": 0.02,
        "seconds": 10,
        "text": "10 secs",
        "total_seconds": 10.777279
      },
      {
        "decimal": "0.00",
        "digital": "0:00:10",
        "hours": 0,
        "minutes": 0,
        "name": "find-replace.component",
        "percent": 0.02,
        "seconds": 10,
        "text": "10 secs",
        "total_seconds": 10.777279
      },
      {
        "decimal": "0.00",
        "digital": "0:00:10",
        "hours": 0,
        "minutes": 0,
        "name": "portlet.module",
        "percent": 0.02,
        "seconds": 10,
        "text": "10 secs",
        "total_seconds": 10.777279
      },
      {
        "decimal": "0.00",
        "digital": "0:00:10",
        "hours": 0,
        "minutes": 0,
        "name": "filters.component",
        "percent": 0.02,
        "seconds": 10,
        "text": "10 secs",
        "total_seconds": 10.777279
      },
      {
        "decimal": "0.00",
        "digital": "0:00:10",
        "hours": 0,
        "minutes": 0,
        "name": "edit-media-dialog.component",
        "percent": 0.02,
        "seconds": 10,
        "text": "10 secs",
        "total_seconds": 10.777279
      },
      {
        "decimal": "0.00",
        "digital": "0:00:10",
        "hours": 0,
        "minutes": 0,
        "name": "export-media-dialog.component",
        "percent": 0.02,
        "seconds": 10,
        "text": "10 secs",
        "total_seconds": 10.777279
      },
      {
        "decimal": "0.00",
        "digital": "0:00:10",
        "hours": 0,
        "minutes": 0,
        "name": "date-picker.component",
        "percent": 0.02,
        "seconds": 10,
        "text": "10 secs",
        "total_seconds": 10.777279
      },
      {
        "decimal": "0.00",
        "digital": "0:00:10",
        "hours": 0,
        "minutes": 0,
        "name": "sentiment-table.component",
        "percent": 0.02,
        "seconds": 10,
        "text": "10 secs",
        "total_seconds": 10.777279
      },
      {
        "decimal": "0.00",
        "digital": "0:00:10",
        "hours": 0,
        "minutes": 0,
        "name": "payment.module",
        "percent": 0.02,
        "seconds": 10,
        "text": "10 secs",
        "total_seconds": 10.777279
      },
      {
        "decimal": "0.00",
        "digital": "0:00:10",
        "hours": 0,
        "minutes": 0,
        "name": "word-cloud.component",
        "percent": 0.02,
        "seconds": 10,
        "text": "10 secs",
        "total_seconds": 10.777279
      },
      {
        "decimal": "0.00",
        "digital": "0:00:10",
        "hours": 0,
        "minutes": 0,
        "name": "common-insight.component",
        "percent": 0.02,
        "seconds": 10,
        "text": "10 secs",
        "total_seconds": 10.777279
      },
      {
        "decimal": "0.00",
        "digital": "0:00:10",
        "hours": 0,
        "minutes": 0,
        "name": "ngx-lottie",
        "percent": 0.02,
        "seconds": 10,
        "text": "10 secs",
        "total_seconds": 10.777279
      },
      {
        "decimal": "0.00",
        "digital": "0:00:10",
        "hours": 0,
        "minutes": 0,
        "name": "create-subscription.component",
        "percent": 0.02,
        "seconds": 10,
        "text": "10 secs",
        "total_seconds": 10.777279
      },
      {
        "decimal": "0.00",
        "digital": "0:00:10",
        "hours": 0,
        "minutes": 0,
        "name": "ngx-toastr",
        "percent": 0.02,
        "seconds": 10,
        "text": "10 secs",
        "total_seconds": 10.777279
      },
      {
        "decimal": "0.00",
        "digital": "0:00:10",
        "hours": 0,
        "minutes": 0,
        "name": "insight-privacy-selector.component",
        "percent": 0.02,
        "seconds": 10,
        "text": "10 secs",
        "total_seconds": 10.777279
      },
      {
        "decimal": "0.00",
        "digital": "0:00:10",
        "hours": 0,
        "minutes": 0,
        "name": "cancel-subscription.component",
        "percent": 0.02,
        "seconds": 10,
        "text": "10 secs",
        "total_seconds": 10.777279
      },
      {
        "decimal": "0.00",
        "digital": "0:00:10",
        "hours": 0,
        "minutes": 0,
        "name": "paywall.component",
        "percent": 0.02,
        "seconds": 10,
        "text": "10 secs",
        "total_seconds": 10.777279
      },
      {
        "decimal": "0.00",
        "digital": "0:00:10",
        "hours": 0,
        "minutes": 0,
        "name": "ngx-text-diff",
        "percent": 0.02,
        "seconds": 10,
        "text": "10 secs",
        "total_seconds": 10.777279
      },
      {
        "decimal": "0.00",
        "digital": "0:00:10",
        "hours": 0,
        "minutes": 0,
        "name": "recorder-analytics-widget.component",
        "percent": 0.02,
        "seconds": 10,
        "text": "10 secs",
        "total_seconds": 10.777279
      },
      {
        "decimal": "0.00",
        "digital": "0:00:10",
        "hours": 0,
        "minutes": 0,
        "name": "widgets",
        "percent": 0.02,
        "seconds": 10,
        "text": "10 secs",
        "total_seconds": 10.777279
      },
      {
        "decimal": "0.00",
        "digital": "0:00:10",
        "hours": 0,
        "minutes": 0,
        "name": "pie-sentiment.component",
        "percent": 0.02,
        "seconds": 10,
        "text": "10 secs",
        "total_seconds": 10.777279
      },
      {
        "decimal": "0.00",
        "digital": "0:00:10",
        "hours": 0,
        "minutes": 0,
        "name": "word-recurrence.component",
        "percent": 0.02,
        "seconds": 10,
        "text": "10 secs",
        "total_seconds": 10.777279
      },
      {
        "decimal": "0.00",
        "digital": "0:00:10",
        "hours": 0,
        "minutes": 0,
        "name": "account-usage.component",
        "percent": 0.02,
        "seconds": 10,
        "text": "10 secs",
        "total_seconds": 10.777279
      },
      {
        "decimal": "0.00",
        "digital": "0:00:10",
        "hours": 0,
        "minutes": 0,
        "name": "share-embed.component",
        "percent": 0.02,
        "seconds": 10,
        "text": "10 secs",
        "total_seconds": 10.777279
      },
      {
        "decimal": "0.00",
        "digital": "0:00:10",
        "hours": 0,
        "minutes": 0,
        "name": "confirm-account-deletion.component",
        "percent": 0.02,
        "seconds": 10,
        "text": "10 secs",
        "total_seconds": 10.777279
      },
      {
        "decimal": "0.00",
        "digital": "0:00:10",
        "hours": 0,
        "minutes": 0,
        "name": "export-account-request.component",
        "percent": 0.02,
        "seconds": 10,
        "text": "10 secs",
        "total_seconds": 10.777279
      },
      {
        "decimal": "0.00",
        "digital": "0:00:10",
        "hours": 0,
        "minutes": 0,
        "name": "approve-multiple-media-dialog.component",
        "percent": 0.02,
        "seconds": 10,
        "text": "10 secs",
        "total_seconds": 10.777279
      },
      {
        "decimal": "0.00",
        "digital": "0:00:10",
        "hours": 0,
        "minutes": 0,
        "name": "ngx-charts",
        "percent": 0.02,
        "seconds": 10,
        "text": "10 secs",
        "total_seconds": 10.777279
      },
      {
        "decimal": "0.00",
        "digital": "0:00:10",
        "hours": 0,
        "minutes": 0,
        "name": "splash-screen.component",
        "percent": 0.02,
        "seconds": 10,
        "text": "10 secs",
        "total_seconds": 10.777279
      },
      {
        "decimal": "0.00",
        "digital": "0:00:10",
        "hours": 0,
        "minutes": 0,
        "name": "lottie-web",
        "percent": 0.02,
        "seconds": 10,
        "text": "10 secs",
        "total_seconds": 10.777279
      },
      {
        "decimal": "0.00",
        "digital": "0:00:10",
        "hours": 0,
        "minutes": 0,
        "name": "call-to-action-buttons.component",
        "percent": 0.02,
        "seconds": 10,
        "text": "10 secs",
        "total_seconds": 10.777279
      },
      {
        "decimal": "0.00",
        "digital": "0:00:10",
        "hours": 0,
        "minutes": 0,
        "name": "import.component",
        "percent": 0.02,
        "seconds": 10,
        "text": "10 secs",
        "total_seconds": 10.777279
      },
      {
        "decimal": "0.00",
        "digital": "0:00:10",
        "hours": 0,
        "minutes": 0,
        "name": "document-sentiment.component",
        "percent": 0.02,
        "seconds": 10,
        "text": "10 secs",
        "total_seconds": 10.777279
      },
      {
        "decimal": "0.00",
        "digital": "0:00:10",
        "hours": 0,
        "minutes": 0,
        "name": "instance.component",
        "percent": 0.02,
        "seconds": 10,
        "text": "10 secs",
        "total_seconds": 10.777279
      },
      {
        "decimal": "0.00",
        "digital": "0:00:10",
        "hours": 0,
        "minutes": 0,
        "name": "drag-drop",
        "percent": 0.02,
        "seconds": 10,
        "text": "10 secs",
        "total_seconds": 10.777279
      },
      {
        "decimal": "0.00",
        "digital": "0:00:10",
        "hours": 0,
        "minutes": 0,
        "name": "api.service",
        "percent": 0.02,
        "seconds": 10,
        "text": "10 secs",
        "total_seconds": 10.443175
      },
      {
        "decimal": "0.00",
        "digital": "0:00:10",
        "hours": 0,
        "minutes": 0,
        "name": "node-fetch",
        "percent": 0.02,
        "seconds": 10,
        "text": "10 secs",
        "total_seconds": 10.276164
      },
      {
        "decimal": "0.00",
        "digital": "0:00:09",
        "hours": 0,
        "minutes": 0,
        "name": "change-password.component",
        "percent": 0.02,
        "seconds": 9,
        "text": "9 secs",
        "total_seconds": 9.243627
      },
      {
        "decimal": "0.00",
        "digital": "0:00:09",
        "hours": 0,
        "minutes": 0,
        "name": "forgot-password.component",
        "percent": 0.02,
        "seconds": 9,
        "text": "9 secs",
        "total_seconds": 9.243627
      },
      {
        "decimal": "0.00",
        "digital": "0:00:09",
        "hours": 0,
        "minutes": 0,
        "name": "auth-notice.component",
        "percent": 0.02,
        "seconds": 9,
        "text": "9 secs",
        "total_seconds": 9.243627
      },
      {
        "decimal": "0.00",
        "digital": "0:00:09",
        "hours": 0,
        "minutes": 0,
        "name": "login.component",
        "percent": 0.02,
        "seconds": 9,
        "text": "9 secs",
        "total_seconds": 9.243627
      },
      {
        "decimal": "0.00",
        "digital": "0:00:09",
        "hours": 0,
        "minutes": 0,
        "name": "register.component",
        "percent": 0.02,
        "seconds": 9,
        "text": "9 secs",
        "total_seconds": 9.243627
      },
      {
        "decimal": "0.00",
        "digital": "0:00:09",
        "hours": 0,
        "minutes": 0,
        "name": "auth.component",
        "percent": 0.02,
        "seconds": 9,
        "text": "9 secs",
        "total_seconds": 9.243627
      },
      {
        "decimal": "0.00",
        "digital": "0:00:09",
        "hours": 0,
        "minutes": 0,
        "name": "verify-user.component",
        "percent": 0.02,
        "seconds": 9,
        "text": "9 secs",
        "total_seconds": 9.243627
      },
      {
        "decimal": "0.00",
        "digital": "0:00:08",
        "hours": 0,
        "minutes": 0,
        "name": "pricing",
        "percent": 0.01,
        "seconds": 8,
        "text": "8 secs",
        "total_seconds": 8.108342
      },
      {
        "decimal": "0.00",
        "digital": "0:00:08",
        "hours": 0,
        "minutes": 0,
        "name": "stepper",
        "percent": 0.01,
        "seconds": 8,
        "text": "8 secs",
        "total_seconds": 8.108342
      },
      {
        "decimal": "0.00",
        "digital": "0:00:06",
        "hours": 0,
        "minutes": 0,
        "name": "userpermission",
        "percent": 0.01,
        "seconds": 6,
        "text": "6 secs",
        "total_seconds": 6.801414
      },
      {
        "decimal": "0.00",
        "digital": "0:00:06",
        "hours": 0,
        "minutes": 0,
        "name": "address.model",
        "percent": 0.01,
        "seconds": 6,
        "text": "6 secs",
        "total_seconds": 6.801414
      },
      {
        "decimal": "0.00",
        "digital": "0:00:05",
        "hours": 0,
        "minutes": 0,
        "name": "sendgrid",
        "percent": 0.01,
        "seconds": 5,
        "text": "5 secs",
        "total_seconds": 5.752752
      },
      {
        "decimal": "0.00",
        "digital": "0:00:05",
        "hours": 0,
        "minutes": 0,
        "name": "generate-password",
        "percent": 0.01,
        "seconds": 5,
        "text": "5 secs",
        "total_seconds": 5.752752
      },
      {
        "decimal": "0.00",
        "digital": "0:00:05",
        "hours": 0,
        "minutes": 0,
        "name": "geolocation",
        "percent": 0.01,
        "seconds": 5,
        "text": "5 secs",
        "total_seconds": 5.752752
      },
      {
        "decimal": "0.00",
        "digital": "0:00:04",
        "hours": 0,
        "minutes": 0,
        "name": "request",
        "percent": 0.01,
        "seconds": 4,
        "text": "4 secs",
        "total_seconds": 4.907155
      },
      {
        "decimal": "0.00",
        "digital": "0:00:04",
        "hours": 0,
        "minutes": 0,
        "name": "cron-job-manager",
        "percent": 0.01,
        "seconds": 4,
        "text": "4 secs",
        "total_seconds": 4.654323
      },
      {
        "decimal": "0.00",
        "digital": "0:00:03",
        "hours": 0,
        "minutes": 0,
        "name": "user-admin.service",
        "percent": 0.01,
        "seconds": 3,
        "text": "3 secs",
        "total_seconds": 3.368692
      },
      {
        "decimal": "0.00",
        "digital": "0:00:03",
        "hours": 0,
        "minutes": 0,
        "name": "paginator",
        "percent": 0.01,
        "seconds": 3,
        "text": "3 secs",
        "total_seconds": 3.368692
      },
      {
        "decimal": "0.00",
        "digital": "0:00:03",
        "hours": 0,
        "minutes": 0,
        "name": "usergroup.model",
        "percent": 0.01,
        "seconds": 3,
        "text": "3 secs",
        "total_seconds": 3.368692
      },
      {
        "decimal": "0.00",
        "digital": "0:00:03",
        "hours": 0,
        "minutes": 0,
        "name": "sort",
        "percent": 0.01,
        "seconds": 3,
        "text": "3 secs",
        "total_seconds": 3.368692
      },
      {
        "decimal": "0.00",
        "digital": "0:00:02",
        "hours": 0,
        "minutes": 0,
        "name": "models",
        "percent": 0,
        "seconds": 2,
        "text": "2 secs",
        "total_seconds": 2.027993
      },
      {
        "decimal": "0.00",
        "digital": "0:00:02",
        "hours": 0,
        "minutes": 0,
        "name": "state",
        "percent": 0,
        "seconds": 2,
        "text": "2 secs",
        "total_seconds": 2.027993
      },
      {
        "decimal": "0.00",
        "digital": "0:00:02",
        "hours": 0,
        "minutes": 0,
        "name": "actions_subject",
        "percent": 0,
        "seconds": 2,
        "text": "2 secs",
        "total_seconds": 2.027993
      },
      {
        "decimal": "0.00",
        "digital": "0:00:02",
        "hours": 0,
        "minutes": 0,
        "name": "reducer_manager",
        "percent": 0,
        "seconds": 2,
        "text": "2 secs",
        "total_seconds": 2.027993
      },
      {
        "decimal": "0.00",
        "digital": "0:00:01",
        "hours": 0,
        "minutes": 0,
        "name": "user.service",
        "percent": 0,
        "seconds": 1,
        "text": "1 sec",
        "total_seconds": 1.961697
      },
      {
        "decimal": "0.00",
        "digital": "0:00:01",
        "hours": 0,
        "minutes": 0,
        "name": "recorder",
        "percent": 0,
        "seconds": 1,
        "text": "1 sec",
        "total_seconds": 1.088076
      },
      {
        "decimal": "0.00",
        "digital": "0:00:01",
        "hours": 0,
        "minutes": 0,
        "name": "is-auth",
        "percent": 0,
        "seconds": 1,
        "text": "1 sec",
        "total_seconds": 1.084605
      },
      {
        "decimal": "0.00",
        "digital": "0:00:01",
        "hours": 0,
        "minutes": 0,
        "name": "userController",
        "percent": 0,
        "seconds": 1,
        "text": "1 sec",
        "total_seconds": 1.084605
      }
    ],
    "editors": [
      {
        "decimal": "3.85",
        "digital": "3:51:19",
        "hours": 3,
        "minutes": 51,
        "name": "VS Code",
        "percent": 100,
        "seconds": 19,
        "text": "3 hrs 51 mins",
        "total_seconds": 13879.948876
      }
    ],
    "grand_total": {
      "decimal": "3.85",
      "digital": "3:51",
      "hours": 3,
      "minutes": 51,
      "text": "3 hrs 51 mins",
      "total_seconds": 13879.948876
    },
    "languages": [
      {
        "decimal": "2.03",
        "digital": "2:02:04",
        "hours": 2,
        "minutes": 2,
        "name": "HTML",
        "percent": 52.77,
        "seconds": 4,
        "text": "2 hrs 2 mins",
        "total_seconds": 7324.772577
      },
      {
        "decimal": "1.68",
        "digital": "1:41:50",
        "hours": 1,
        "minutes": 41,
        "name": "TypeScript",
        "percent": 44.03,
        "seconds": 50,
        "text": "1 hr 41 mins",
        "total_seconds": 6110.705914
      },
      {
        "decimal": "0.08",
        "digital": "0:05:13",
        "hours": 0,
        "minutes": 5,
        "name": "SCSS",
        "percent": 2.26,
        "seconds": 13,
        "text": "5 mins",
        "total_seconds": 313.983991
      },
      {
        "decimal": "0.03",
        "digital": "0:02:08",
        "hours": 0,
        "minutes": 2,
        "name": "Bash",
        "percent": 0.92,
        "seconds": 8,
        "text": "2 mins",
        "total_seconds": 128.136141
      },
      {
        "decimal": "0.00",
        "digital": "0:00:02",
        "hours": 0,
        "minutes": 0,
        "name": "JSON",
        "percent": 0.02,
        "seconds": 2,
        "text": "2 secs",
        "total_seconds": 2.350253
      },
      {
        "decimal": "0.00",
        "digital": "0:00:00",
        "hours": 0,
        "minutes": 0,
        "name": "Other",
        "percent": 0,
        "seconds": 0,
        "text": "0 secs",
        "total_seconds": 0
      }
    ],
    "machines": [
      {
        "decimal": "3.85",
        "digital": "3:51:19",
        "hours": 3,
        "machine_name_id": "67867970-5c5b-49fb-a919-bca954366b77",
        "minutes": 51,
        "name": "Vatsal-Shah-MBP.ht.home",
        "percent": 100,
        "seconds": 19,
        "text": "3 hrs 51 mins",
        "total_seconds": 13879.948876
      }
    ],
    "operating_systems": [
      {
        "decimal": "3.85",
        "digital": "3:51:19",
        "hours": 3,
        "minutes": 51,
        "name": "Mac",
        "percent": 100,
        "seconds": 19,
        "text": "3 hrs 51 mins",
        "total_seconds": 13879.948876
      }
    ],
    "projects": [
      {
        "color": null,
        "decimal": "3.42",
        "digital": "3:25:43",
        "hours": 3,
        "minutes": 25,
        "name": "speak-client",
        "percent": 88.93,
        "seconds": 43,
        "text": "3 hrs 25 mins",
        "total_seconds": 12343.266262
      },
      {
        "color": null,
        "decimal": "0.42",
        "digital": "0:25:36",
        "hours": 0,
        "minutes": 25,
        "name": "speak-server",
        "percent": 11.07,
        "seconds": 36,
        "text": "25 mins",
        "total_seconds": 1536.682614
      }
    ],
    "range": {
      "date": "2022-09-27",
      "end": "2022-09-28T03:59:59Z",
      "start": "2022-09-27T04:00:00Z",
      "text": "Today",
      "timezone": "America/Toronto"
    }
  }
]