{
  "2021-10-10": {
    "steps": 11391,
    "total": 337,
    "cal_active": 541,
    "cal_total": 2715,
    "score": 81
  },
  "2021-10-11": {
    "steps": 10301,
    "total": 377,
    "cal_active": 505,
    "cal_total": 2644,
    "score": 88
  },
  "2021-10-12": {
    "steps": 8074,
    "total": 225,
    "cal_active": 353,
    "cal_total": 2464,
    "score": 82
  },
  "2021-10-13": {
    "steps": 10704,
    "total": 234,
    "cal_active": 649,
    "cal_total": 2781,
    "score": 80
  },
  "2021-10-14": {
    "steps": 8146,
    "total": 235,
    "cal_active": 361,
    "cal_total": 2504,
    "score": 72
  },
  "2021-10-15": {
    "steps": 12934,
    "total": 350,
    "cal_active": 731,
    "cal_total": 2967,
    "score": 79
  },
  "2021-10-16": {
    "steps": 2889,
    "total": 96,
    "cal_active": 134,
    "cal_total": 2063,
    "score": 81
  }
}