[
  {
    "summary_date": "2022-02-14",
    "period_id": 1,
    "is_longest": 1,
    "timezone": 330,
    "bedtime_end": "2022-02-15T09:58:30+05:30",
    "bedtime_start": "2022-02-15T02:04:30+05:30",
    "breath_average": 13.25,
    "duration": 28440,
    "total": 25170,
    "awake": 3270,
    "rem": 4890,
    "deep": 6210,
    "light": 14070,
    "midpoint_time": 13920,
    "efficiency": 89,
    "restless": 35,
    "onset_latency": 90,
    "hr_5min": [
      67,
      65,
      63,
      64,
      65,
      64,
      65,
      66,
      66,
      64,
      65,
      65,
      67,
      64,
      64,
      64,
      63,
      64,
      65,
      73,
      72,
      69,
      68,
      66,
      65,
      64,
      65,
      65,
      64,
      64,
      64,
      63,
      63,
      63,
      63,
      64,
      64,
      61,
      65,
      66,
      64,
      69,
      68,
      68,
      64,
      64,
      63,
      64,
      64,
      65,
      66,
      64,
      63,
      64,
      63,
      63,
      64,
      64,
      64,
      64,
      66,
      67,
      70,
      65,
      65,
      67,
      66,
      64,
      63,
      61,
      65,
      65,
      65,
      66,
      67,
      63,
      61,
      63,
      61,
      64,
      62,
      62,
      63,
      62,
      63,
      65,
      69,
      66,
      65,
      67,
      66,
      66,
      65,
      67,
      79
    ],
    "hr_average": 64.99,
    "hr_lowest": 61,
    "hypnogram_5min": "22221111122122222211423422211112222222224432222222221111111133322242233333322222222222433333344",
    "rmssd": 26,
    "rmssd_5min": [
      21,
      25,
      21,
      17,
      18,
      18,
      18,
      22,
      23,
      36,
      20,
      25,
      33,
      31,
      31,
      36,
      22,
      23,
      19,
      20,
      13,
      32,
      18,
      26,
      25,
      16,
      17,
      17,
      18,
      18,
      31,
      22,
      17,
      22,
      24,
      24,
      32,
      27,
      19,
      25,
      27,
      18,
      24,
      29,
      19,
      18,
      24,
      25,
      26,
      21,
      35,
      27,
      22,
      31,
      24,
      24,
      26,
      30,
      37,
      35,
      35,
      27,
      21,
      31,
      26,
      29,
      28,
      37,
      26,
      35,
      28,
      38,
      34,
      42,
      45,
      35,
      25,
      36,
      36,
      35,
      35,
      30,
      31,
      34,
      28,
      39,
      47,
      32,
      25,
      32,
      31,
      25,
      30,
      33,
      29
    ],
    "score": 68,
    "score_alignment": 20,
    "score_deep": 96,
    "score_disturbances": 61,
    "score_efficiency": 93,
    "score_latency": 64,
    "score_rem": 67,
    "score_total": 72,
    "temperature_deviation": -0.11,
    "temperature_trend_deviation": -0.01,
    "bedtime_start_delta": 7470,
    "bedtime_end_delta": 35910,
    "midpoint_at_delta": 21390,
    "temperature_delta": -0.11
  }
]