{
  "2021-09-26": {
    "Communication & Scheduling": 8662,
    "Utilities": 4407,
    "Entertainment": 4116,
    "Reference & Learning": 3420,
    "Uncategorized": 2738,
    "Social Networking": 2370,
    "Shopping": 9,
    "Business": 5
  },
  "2021-09-27": {
    "Software Development": 11940,
    "Communication & Scheduling": 4646,
    "Business": 3668,
    "Utilities": 3345,
    "Uncategorized": 3121,
    "Social Networking": 1639,
    "Reference & Learning": 1300,
    "Entertainment": 338,
    "Design & Composition": 89,
    "News & Opinion": 2
  },
  "2021-09-28": {
    "Software Development": 16405,
    "Entertainment": 7689,
    "Communication & Scheduling": 4901,
    "Uncategorized": 4770,
    "Business": 4451,
    "Social Networking": 3753,
    "Utilities": 2090,
    "Reference & Learning": 973,
    "Design & Composition": 612,
    "News & Opinion": 432,
    "Shopping": 37
  },
  "2021-09-29": {
    "Software Development": 17239,
    "Communication & Scheduling": 10107,
    "Utilities": 4676,
    "Business": 3428,
    "Reference & Learning": 3179,
    "Social Networking": 3167,
    "Uncategorized": 2439,
    "Entertainment": 1312,
    "News & Opinion": 645,
    "Design & Composition": 237,
    "Shopping": 98
  },
  "2021-09-30": {
    "Software Development": 17587,
    "Communication & Scheduling": 3152,
    "Uncategorized": 1881,
    "Business": 1446,
    "Social Networking": 756,
    "Utilities": 303,
    "Reference & Learning": 303,
    "Design & Composition": 261,
    "News & Opinion": 128,
    "Shopping": 102,
    "Entertainment": 8
  },
  "2021-10-1": {},
  "2021-10-2": {}
}