[
  {
    "summary_date": "2021-12-25",
    "period_id": 0,
    "is_longest": 1,
    "timezone": 330,
    "bedtime_end": "2021-12-26T07:33:51+05:30",
    "bedtime_start": "2021-12-26T02:17:51+05:30",
    "breath_average": 13.625,
    "duration": 18960,
    "total": 14670,
    "awake": 4290,
    "rem": 3210,
    "deep": 2760,
    "light": 8700,
    "midpoint_time": 9750,
    "efficiency": 77,
    "restless": 31,
    "onset_latency": 420,
    "hr_5min": [
      82,
      81,
      80,
      79,
      76,
      71,
      72,
      71,
      70,
      73,
      74,
      74,
      73,
      70,
      69,
      70,
      70,
      73,
      68,
      68,
      68,
      68,
      68,
      68,
      69,
      67,
      68,
      68,
      68,
      67,
      67,
      66,
      72,
      71,
      73,
      78,
      71,
      73,
      75,
      74,
      70,
      69,
      69,
      68,
      69,
      69,
      69,
      70,
      70,
      70,
      70,
      70,
      70,
      71,
      72,
      77,
      74,
      71,
      69,
      72,
      74,
      70,
      0,
      0
    ],
    "hr_average": 71.23,
    "hr_lowest": 66,
    "hypnogram_5min": "4222442222334422222222113222244222233334422222111111124333223444",
    "rmssd": 18,
    "rmssd_5min": [
      9,
      9,
      11,
      17,
      18,
      13,
      11,
      12,
      13,
      17,
      17,
      22,
      17,
      22,
      17,
      12,
      14,
      25,
      19,
      15,
      16,
      18,
      29,
      37,
      25,
      27,
      29,
      19,
      22,
      28,
      30,
      27,
      24,
      18,
      15,
      13,
      25,
      18,
      21,
      29,
      20,
      23,
      21,
      16,
      18,
      16,
      15,
      16,
      15,
      15,
      16,
      17,
      32,
      31,
      20,
      19,
      21,
      28,
      22,
      23,
      31,
      29,
      0,
      0
    ],
    "score": 48,
    "score_alignment": 39,
    "score_deep": 46,
    "score_disturbances": 64,
    "score_efficiency": 65,
    "score_latency": 78,
    "score_rem": 43,
    "score_total": 31,
    "temperature_deviation": 0.04,
    "temperature_trend_deviation": 0.15,
    "bedtime_start_delta": 8271,
    "bedtime_end_delta": 27231,
    "midpoint_at_delta": 18021,
    "temperature_delta": 0.04
  }
]