{
  "2021": {
    "Email": 328262,
    "Browsers": 361993,
    "General Social Networking": 548345,
    "Professional Networking": 131497,
    "Maps & Regional": 65441,
    "Video": 405766,
    "Uncategorized": 555344,
    "Instant Message": 648077,
    "General Utilities": 385354,
    "Search": 154801,
    "Health & Medicine": 38431,
    "Music": 32637,
    "General Shopping": 59757,
    "Clothes & Personal": 6491,
    "Voice Chat": 1676,
    "Calendars": 26174,
    "General Reference & Learning": 33659,
    "General Business": 180969,
    "Photos": 31390,
    "Engineering & Technology": 68526,
    "Science & Technology": 8040,
    "Project Management": 50160,
    "General Entertainment": 117474,
    "General Communication & Scheduling": 17505,
    "Business": 747,
    "General Software Development": 456345,
    "Internet Utilities": 19172,
    "Writing": 73738,
    "Intelligence": 31553,
    "General News & Opinion": 22817,
    "Meetings": 359405,
    "Games": 16286,
    "Accounting": 22564,
    "Business & Finance": 912,
    "Editing & IDEs": 938936,
    "Video Editing": 8909,
    "Other": 21626,
    "Sports": 1596,
    "Systems Operations": 18699,
    "Graphic Design": 4608,
    "General Design & Composition": 6603,
    "Presentation": 12458,
    "Electronics": 1086,
    "Operations": 29257,
    "Travel & Outdoors": 10305,
    "Administration": 860,
    "Anti-Virus & Spyware": 1052,
    "Customer Relations": 1453,
    "Quality Assurance": 567,
    "Marketing": 530,
    "Society": 8,
    "Legal & Gov't": 4150,
    "Unknown": 262,
    "Data Modeling & Analysis": 10777,
    "Design & Planning": 2505,
    "File Sharing": 45,
    "Comedy": 999,
    "Employment": 346,
    "Audio Editing": 3,
    "Sales": 12,
    "Home & Garden": 75,
    "Food": 632,
    "Regional": 9,
    "Entertainment": 14
  },
  "2022": {
    "Writing": 29157,
    "Operations": 3316,
    "Uncategorized": 112471,
    "Professional Networking": 13947,
    "Email": 67502,
    "Other": 15823,
    "Project Management": 11964,
    "Instant Message": 15234,
    "General Reference & Learning": 8652,
    "Search": 34792,
    "Calendars": 5046,
    "General Business": 50362,
    "Browsers": 23192,
    "General Utilities": 44579,
    "Internet Utilities": 7202,
    "Games": 211,
    "General Communication & Scheduling": 1735,
    "Intelligence": 12833,
    "Presentation": 918,
    "General Software Development": 226618,
    "General News & Opinion": 7604,
    "General Social Networking": 4914,
    "Video": 7248,
    "Customer Relations": 1582,
    "Photos": 440,
    "Engineering & Technology": 15768,
    "General Shopping": 3262,
    "General Design & Composition": 114,
    "Editing & IDEs": 373266,
    "Business & Finance": 280,
    "Anti-Virus & Spyware": 455,
    "Meetings": 167843,
    "Systems Operations": 10285,
    "Data Modeling & Analysis": 29310,
    "Music": 651,
    "Travel & Outdoors": 2684,
    "Legal & Gov't": 182,
    "Graphic Design": 739,
    "Design & Planning": 1156,
    "Video Editing": 10,
    "Accounting": 5657,
    "General Entertainment": 7440,
    "Science & Technology": 511,
    "Unknown": 2,
    "Communications": 66774,
    "Sports": 5,
    "Electronics": 1496,
    "Clothes & Personal": 10,
    "File Sharing": 72,
    "Marketing": 164,
    "Engineering & Drafting": 10,
    "Employment": 15,
    "Quality Assurance": 45,
    "Administration": 108
  }
}