[
  {
    "awake": 8880,
    "bedtime_end": "2021-01-08T11:16:43-05:00",
    "bedtime_end_delta": 40603,
    "bedtime_start": "2021-01-08T00:57:43-05:00",
    "bedtime_start_delta": 3463,
    "breath_average": 13.5,
    "deep": 4890,
    "duration": 37140,
    "efficiency": 76,
    "hr_5min": [
      82,
      82,
      84,
      85,
      83,
      83,
      84,
      83,
      82,
      84,
      80,
      82,
      79,
      78,
      78,
      78,
      79,
      80,
      80,
      84,
      86,
      83,
      82,
      82,
      80,
      81,
      80,
      81,
      82,
      80,
      80,
      80,
      82,
      82,
      85,
      84,
      87,
      81,
      80,
      80,
      80,
      79,
      79,
      79,
      79,
      79,
      79,
      79,
      78,
      77,
      76,
      80,
      81,
      80,
      76,
      76,
      76,
      77,
      79,
      79,
      79,
      79,
      81,
      84,
      81,
      80,
      82,
      80,
      86,
      82,
      81,
      79,
      77,
      78,
      79,
      79,
      80,
      77,
      78,
      78,
      79,
      79,
      79,
      82,
      80,
      81,
      82,
      80,
      82,
      82,
      82,
      80,
      77,
      83,
      81,
      79,
      78,
      79,
      79,
      81,
      84,
      0,
      0,
      0,
      0,
      0,
      0,
      86,
      83,
      84,
      84,
      83,
      83,
      80,
      82,
      77,
      79,
      81,
      78,
      76,
      80,
      86,
      86,
      0
    ],
    "hr_average": 80.62,
    "hr_lowest": 76,
    "hypnogram_5min": "4222111113322221113322211122222224432222222222312234432222211242333334222222332222223444422224222333244444444434422222222444",
    "is_longest": 1,
    "light": 17340,
    "midpoint_at_delta": 19783,
    "midpoint_time": 16320,
    "onset_latency": 510,
    "period_id": 1,
    "rem": 6030,
    "restless": 44,
    "rmssd": 16,
    "rmssd_5min": [
      14,
      18,
      15,
      16,
      13,
      10,
      11,
      12,
      15,
      17,
      18,
      22,
      19,
      16,
      17,
      16,
      16,
      21,
      16,
      13,
      12,
      13,
      14,
      15,
      18,
      18,
      18,
      14,
      17,
      16,
      17,
      18,
      15,
      13,
      13,
      15,
      10,
      12,
      13,
      13,
      14,
      12,
      11,
      11,
      11,
      11,
      10,
      12,
      12,
      16,
      15,
      17,
      14,
      17,
      19,
      18,
      18,
      15,
      13,
      14,
      21,
      18,
      16,
      15,
      14,
      16,
      17,
      17,
      27,
      18,
      13,
      15,
      17,
      19,
      16,
      19,
      22,
      24,
      17,
      18,
      17,
      16,
      18,
      19,
      18,
      31,
      24,
      23,
      17,
      17,
      18,
      16,
      21,
      19,
      19,
      19,
      19,
      18,
      18,
      25,
      15,
      0,
      0,
      0,
      0,
      0,
      0,
      12,
      18,
      16,
      19,
      20,
      15,
      16,
      18,
      26,
      22,
      23,
      22,
      27,
      25,
      15,
      11,
      0
    ],
    "score": 70,
    "score_alignment": 25,
    "score_deep": 81,
    "score_disturbances": 51,
    "score_efficiency": 62,
    "score_latency": 83,
    "score_rem": 83,
    "score_total": 84,
    "summary_date": "2021-01-07",
    "temperature_delta": 0.7,
    "temperature_deviation": 0.7,
    "temperature_trend_deviation": 0.62,
    "timezone": -300,
    "total": 28260
  }
]